python_event_bus/__init__.py
python_event_bus/bus.py
python_event_bus/exceptions.py
python_event_bus-1.2.0.dist-info/METADATA
python_event_bus-1.2.0.dist-info/WHEEL
python_event_bus-1.2.0.dist-info/licenses/LICENSE
python_event_bus-1.2.0.dist-info/RECORD
