Metadata-Version: 2.1
Name: python-event-bus
Version: 1.2.0
Summary: python-event-bus makes communication between python classes easier.
Author: mxngo
License-File: LICENSE
Classifier: Development Status :: 5 - Production/Stable
Classifier: License :: OSI Approved :: MIT License
Classifier: Operating System :: OS Independent
Classifier: Programming Language :: Python :: 3
Classifier: Topic :: Utilities
Requires-Python: >=3.10
